ouro/__init__.py
ouro/__version__.py
ouro/_constants.py
ouro/_exceptions.py
ouro/_logs.py
ouro/_resource.py
ouro/_types.py
ouro/_utils.py
ouro/client.py
ouro/config.py
ouro/py.typed
ouro/models/__init__.py
ouro/models/action.py
ouro/models/asset.py
ouro/models/file.py
ouro/models/route.py
ouro/models/service.py
ouro/realtime/__init__.py
ouro/realtime/websocket.py
ouro/resources/__init__.py
ouro/resources/assets.py
ouro/resources/comments.py
ouro/resources/content.py
ouro/resources/conversations.py
ouro/resources/datasets.py
ouro/resources/files.py
ouro/resources/posts.py
ouro/resources/routes.py
ouro/resources/services.py
ouro/resources/users.py
ouro/utils/__init__.py
ouro/utils/openapi.py
ouro/utils/plotly.py
ouro_py-0.3.13.dist-info/METADATA
ouro_py-0.3.13.dist-info/WHEEL
ouro_py-0.3.13.dist-info/licenses/LICENSE
ouro_py-0.3.13.dist-info/RECORD
