Metadata-Version: 2.3
Name: ouro-py
Version: 0.3.13
Summary: The official Python library for the Ouro API
Project-URL: Homepage, https://github.com/ourofoundation/ouro-py
Project-URL: Repository, https://github.com/ourofoundation/ouro-py
Project-URL: PyPI, https://pypi.org/project/ouro-py
Author-email: Matt Moderwell <matt@ouro.foundation>
License: MIT
License-File: LICENSE
Keywords: ouro
Classifier: License :: OSI Approved :: MIT License
Classifier: Operating System :: OS Independent
Classifier: Programming Language :: Python :: 3
Requires-Python: >=3.7
Requires-Dist: anyio
Requires-Dist: distro
Requires-Dist: httpx
Requires-Dist: numpy
Requires-Dist: pandas
Requires-Dist: postgrest
Requires-Dist: pydantic
Requires-Dist: python-dotenv
Requires-Dist: python-socketio[asyncio-client]
Requires-Dist: supabase
Requires-Dist: tabulate
